RISC-V_core/main.v
`timescale 1ns/100ps
module control(
    input [31:0]instr,

    output reg [11:0]imm12,
    output reg rf_w,
    output reg alu_op
);

//Поля из инструкций, отвечающие за то, какая инструкция должна исполняться
wire [6:0]opcode = instr[6:0];
wire [2:0]funct3 = instr[14:12];

 
always @(*) begin
    rf_w = 1'b0;
    alu_op = 1'b0;
    imm12 = 12'b0;

    casez({funct3, opcode}) 
        10'b000_0010011: begin
            rf_w = 1'b1;
            alu_op  = 1'b1;
            imm12 = instr[31:20];
        end
        default: ;
    endcase
end

endmodule

module core(
    input clk,
    input [31:0]instr,
    input [31:0]last_pc,

    output [31:0]instr_addr
);

reg [31:0]pc = 0;
assign instr_addr = pc;
always @(posedge clk) begin
    pc <= (pc == last_pc) ? pc : pc + 16;
    $display("[%h] %h", pc, instr);
end

wire [4:0]rd = instr[11:7];
wire [4:0]rs1 = instr[19:15];
wire [4:0]rs2 = instr[24:20];

wire [31:0]alu_res;
wire [31:0]alu_b_src = imm32;

alu alu(.src_a(rf_rdata0), .src_b(alu_b_src), .op(alu_op), .out(alu_res));

wire [31:0]rf_rdata0;
wire [31:0]rf_rdata1;
wire [4:0]rf_raddr0 = rs1;
wire [4:0]rf_raddr1 = rs2;
wire [31:0]rf_wdata = alu_res;
wire [4:0]rf_waddr = rd;
wire rf_w;

reg_file rf(
    .clk(clk),
    .raddr0(rf_raddr0), .rdata0(rf_rdata0),
    .raddr1(rf_raddr1), .rdata1(rf_rdata1),
    .waddr(rf_waddr), .wdata(rf_wdata), .we(rf_w)
);

wire [11:0]imm12;
wire [31:0]imm32 = { {20{imm12[11]} }, imm12 };


control control(
    .instr(instr),
    .imm12(imm12),
    .rf_w(rf_w),
    .alu_op(alu_op)
);

endmodule



module cpu_top(
    input wire clk
);

wire [31:0]instr_addr;
wire [31:0]instr_data;
rom rom(.addr(instr_addr[31:2]), .q(instr_data));

core core(
    .clk(clk),
    .instr(instr_data), .last_pc(32'h70),
    .instr_addr(instr_addr)
);

endmodule


module testbench();

reg clk = 1'b0;

always begin
    #1 clk = ~clk;
end

cpu_top cpu_top(.clk(clk));

initial begin
    $dumpvars;
    #16 $finish;
end

endmodule

RISC-V_core/reg_file.v
module reg_file(        
    input clk,          
    input [4:0]raddr0,   // Адрес чтения №0
    input [4:0]raddr1,   // Адрес чтения №1
    input [4:0]waddr,    // Адрес записи
    input [31:0]wdata,   // Данные для записи
    input we,            // Вход разрешения записи
                        
    output [31:0]rdata0, // Прочитанные данные №0
    output [31:0]rdata1  // Прочитанные данные №1
);

reg [31:0]regs[0:31];

assign rdata0 = (raddr0 == 0) ? 0 : regs[raddr0];
assign rdata1 = (raddr1 == 0) ? 0 : regs[raddr1];

always @(posedge clk) begin
    if (we && waddr != 0) begin
        regs[waddr] <= wdata;
        $display("x%0d = %h", waddr, wdata);
    end
end

endmodule

RISC-V_core/alu.v
module alu(
    input [31:0]src_a,
    input [31:0]src_b,
    input op,
    output reg [31:0]out
);

always @(*) begin
    case(op)
        1'b0: out = src_a;
        1'b1: out = src_a + src_b;
    endcase
end

endmodule

RISC-V_core/rom.v
module rom #(parameter LENGTH = 8, parameter WIDTH = 32)(
    input [31:0]addr,

    output [WIDTH - 1:0]q
);

reg [WIDTH - 1:0]mem[0:LENGTH - 1];

assign q = mem[addr[31:2]]; //Адресация по старшим битам

initial begin
    $readmemh("addi.txt", mem);
end

endmodule

module rom_fetcher(
    input clk,
    output [15:0]q
);

reg [7:0]pc = 0;
wire [7:0]pc_next = pc + 1;

rom #(.WIDTH(16)) rom(.addr(pc), .q(q));

always @(posedge clk) begin
  pc <= pc_next;
end

endmodule

RISC-V_core/dump.vcd
$date
	Fri Apr 18 22:38:13 2025
$end
$version
	Icarus Verilog
$end
$timescale
	100ps
$end
$scope module rom_fetcher $end
$var wire 1 ! clk $end
$var wire 16 " q [15:0] $end
$var wire 8 # pc_next [7:0] $end
$var reg 8 $ pc [7:0] $end
$scope module rom $end
$var wire 32 % addr [31:0] $end
$var wire 16 & q [15:0] $end
$var parameter 32 ' LENGTH $end
$var parameter 32 ( WIDTH $end
$upscope $end
$upscope $end
$scope module testbench $end
$var reg 1 ) clk $end
$scope module cpu_top $end
$var wire 1 ) clk $end
$var wire 32 * instr_data [31:0] $end
$var wire 32 + instr_addr [31:0] $end
$scope module core $end
$var wire 32 , alu_b_src [31:0] $end
$var wire 1 ) clk $end
$var wire 32 - last_pc [31:0] $end
$var wire 5 . rf_raddr0 [4:0] $end
$var wire 5 / rf_raddr1 [4:0] $end
$var wire 5 0 rf_waddr [4:0] $end
$var wire 32 1 rf_wdata [31:0] $end
$var wire 5 2 rs2 [4:0] $end
$var wire 5 3 rs1 [4:0] $end
$var wire 1 4 rf_w $end
$var wire 32 5 rf_rdata1 [31:0] $end
$var wire 32 6 rf_rdata0 [31:0] $end
$var wire 5 7 rd [4:0] $end
$var wire 32 8 instr_addr [31:0] $end
$var wire 32 9 instr [31:0] $end
$var wire 32 : imm32 [31:0] $end
$var wire 12 ; imm12 [11:0] $end
$var wire 32 < alu_res [31:0] $end
$var wire 1 = alu_op $end
$var reg 32 > pc [31:0] $end
$scope module alu $end
$var wire 32 ? src_b [31:0] $end
$var wire 32 @ src_a [31:0] $end
$var wire 1 = op $end
$var reg 32 A out [31:0] $end
$upscope $end
$scope module control $end
$var wire 7 B opcode [6:0] $end
$var wire 32 C instr [31:0] $end
$var wire 3 D funct3 [2:0] $end
$var reg 1 = alu_op $end
$var reg 12 E imm12 [11:0] $end
$var reg 1 4 rf_w $end
$upscope $end
$scope module rf $end
$var wire 1 ) clk $end
$var wire 5 F raddr0 [4:0] $end
$var wire 5 G raddr1 [4:0] $end
$var wire 5 H waddr [4:0] $end
$var wire 32 I wdata [31:0] $end
$var wire 1 4 we $end
$var wire 32 J rdata1 [31:0] $end
$var wire 32 K rdata0 [31:0] $end
$upscope $end
$upscope $end
$scope module rom $end
$var wire 32 L addr [31:0] $end
$var wire 32 M q [31:0] $end
$var parameter 32 N LENGTH $end
$var parameter 32 O WIDTH $end
$upscope $end
$upscope $end
$upscope $end
$enddefinitions $end
$comment Show the parameter values. $end
$dumpall
b100000 O
b1000 N
b10000 (
b1000 '
$end
#0
$dumpvars
b101100000000001010010011 M
b0 L
b0 K
bx J
b1011 I
b101 H
b1011 G
b0 F
b1011 E
b0 D
b101100000000001010010011 C
b10011 B
b1011 A
b0 @
b1011 ?
b0 >
1=
b1011 <
b1011 ;
b1011 :
b101100000000001010010011 9
b0 8
b101 7
b0 6
bx 5
14
b0 3
b1011 2
b1011 1
b101 0
b1011 /
b0 .
b1110000 -
b1011 ,
b0 +
b101100000000001010010011 *
0)
b1010010011 &
b0 %
b0 $
b1 #
b1010010011 "
z!
$end
#10
b0 5
b0 J
b0 1
b0 I
b0 <
b0 A
b0 /
b0 G
b0 2
b111 0
b111 H
b111 7
b0 ,
b0 ?
b0 :
b0 ;
b0 E
1=
14
b1110010011 *
b1110010011 9
b1110010011 C
b1110010011 M
b100 L
b10000 +
b10000 8
b10000 >
1)
#20
0)
#30
bx 5
bx J
b1011 6
b1011 @
b1011 K
b10100 1
b10100 I
b10100 <
b10100 A
b1001 /
b1001 G
b1001 2
b101 .
b101 F
b101 3
b1001 ,
b1001 ?
b1001 :
b1001 ;
b1001 E
1=
14
b100100101000001110010011 *
b100100101000001110010011 9
b100100101000001110010011 C
b100100101000001110010011 M
b1000 L
b100000 +
b100000 8
b100000 >
1)
#40
0)
#50
b0 5
b0 J
b0 6
b0 @
b0 K
b0 1
b0 I
b0 <
b0 A
b0 /
b0 G
b0 2
b0 .
b0 F
b0 3
b0 0
b0 H
b0 7
b0 ,
b0 ?
b0 :
b0 ;
b0 E
1=
14
b10011 *
b10011 9
b10011 C
b10011 M
b1100 L
b110000 +
b110000 8
b110000 >
1)
#60
0)
#70
b1011 0
b1011 H
b1011 7
1=
14
b10110010011 *
b10110010011 9
b10110010011 C
b10110010011 M
b10000 L
b1000000 +
b1000000 8
b1000000 >
1)
#80
0)
#90
b10100 1
b10100 I
b10100 <
b10100 A
b10100 6
b10100 @
b10100 K
b111 .
b111 F
b111 3
1=
14
b111000010110010011 *
b111000010110010011 9
b111000010110010011 C
b111000010110010011 M
b10100 L
b1010000 +
b1010000 8
b1010000 >
1)
#100
0)
#110
b0 1
b0 I
b0 <
b0 A
b0 6
b0 @
b0 K
b1101111 B
b0 .
b0 F
b0 3
b0 0
b0 H
b0 7
0=
04
b1101111 *
b1101111 9
b1101111 C
b1101111 M
b11000 L
b1100000 +
b1100000 8
b1100000 >
1)
#120
0)
#130
1=
14
b10011 B
b10011 *
b10011 9
b10011 C
b10011 M
b11100 L
b1110000 +
b1110000 8
b1110000 >
1)
