elbrus/task/ram.v
`timescale 1ns/100ps
module joke #(
    parameter MEM_SIZE = 6, 
    parameter DATA_W = 10, 
    parameter ADDR_SIZE = MEM_SIZE
)(
    input write,
    input [DATA_W - 1:0]datain,
    input [ADDR_SIZE - 1:0]addr_w,
    input read,
    input [ADDR_SIZE - 1:0]addr_r,

    input clk,

    output reg [DATA_W - 1:0]dataout
);

reg [ADDR_SIZE - 1:0]addr_r_prev;            // последний считанный адрес
reg [DATA_W - 1:0]mem[0:MEM_SIZE - 1];

always @(posedge clk) begin

    if (write && !read) begin
        mem[addr_w] <= datain;              //признак записи - записываем в ячейку addr_w
        dataout <= mem[addr_r_prev];        //нет пр. чтения - читаем по последнему считанному адресу (addr_r_prev)
    end

    if (read && !write) begin
        addr_r_prev <= addr_r;
        dataout <= mem[addr_r];
    end

    if (read && write) begin
        addr_r_prev <= addr_r;
        mem[addr_w] <= datain;
        dataout <= mem[addr_r];
    end

    else begin
        dataout <= mem[addr_r_prev];
    end
end

endmodule



module test();

localparam MEM_SIZE = 6;
localparam ADDR_SIZE = MEM_SIZE;
localparam DATA_W = 7;
reg clk = 1'b1;

always begin
    #1 clk = ~clk;
end

reg w, r;
reg [ADDR_SIZE - 1:0]addr_r;
reg [ADDR_SIZE - 1:0]addr_w;
reg [DATA_W - 1:0]d_in;
wire [DATA_W - 1:0]d_out;

joke #(.MEM_SIZE(MEM_SIZE), .ADDR_SIZE(ADDR_SIZE), .DATA_W(DATA_W)) joke (
    .write(w),
    .datain(d_in),
    .dataout(d_out),
    .clk(clk),
    .addr_r(addr_r),
    .addr_w(addr_w),
    .read(r)
);

initial begin
    $dumpvars;

    {d_in, w, r, addr_w, addr_r} = 0;

    #2
    d_in = 7'b0000001;
    w = 1;
    r = 1;
    addr_w = 1;
    addr_r = 1;
    #2 $display(d_out);

    #2
    d_in = 7'b0000010;
    w = 0;
    r = 0;
    addr_w = 2;
    addr_r = 1;
    #2 $display(d_out);

    #2
    d_in = 7'b0000011;
    w = 1;
    r = 1;
    addr_w = 5;
    addr_r = 2;
    #2 $display(d_out);

    #2
    d_in = 7'b0000100;
    w = 1;
    r = 1;
    addr_w = 2;
    addr_r = 5;
    #2 $display(d_out);

    #2
    d_in = 7'b000101;
    w = 0;
    r = 0;
    addr_w = 4;
    addr_r = 2;
    #2 $display(d_out);

    #2
    d_in = 7'b100111;
    w = 1;
    r = 0;
    addr_w = 3;
    addr_r = 4;
    #2 $display(d_out);

    #2
    d_in = 7'b000000;
    w = 0;
    r = 1;
    addr_r = 3;
    #2 $display(d_out);

    #2 
    d_in = 7'b000000;
    w = 0;
    r = 0;
    addr_r = 5;
    #2 $display(d_out);


    #50 $finish;
end

endmodule

elbrus/task/dump.vcd
$date
	Sat May 17 12:51:31 2025
$end
$version
	Icarus Verilog
$end
$timescale
	100ps
$end
$scope module test $end
$var wire 7 ! d_out [6:0] $end
$var parameter 32 " ADDR_SIZE $end
$var parameter 32 # DATA_W $end
$var parameter 32 $ MEM_SIZE $end
$var reg 6 % addr_r [5:0] $end
$var reg 6 & addr_w [5:0] $end
$var reg 1 ' clk $end
$var reg 7 ( d_in [6:0] $end
$var reg 1 ) r $end
$var reg 1 * w $end
$scope module joke $end
$var wire 6 + addr_r [5:0] $end
$var wire 6 , addr_w [5:0] $end
$var wire 1 ' clk $end
$var wire 7 - datain [6:0] $end
$var wire 1 ) read $end
$var wire 1 * write $end
$var parameter 32 . ADDR_SIZE $end
$var parameter 32 / DATA_W $end
$var parameter 32 0 MEM_SIZE $end
$var reg 6 1 addr_r_prev [5:0] $end
$var reg 7 2 dataout [6:0] $end
$upscope $end
$upscope $end
$enddefinitions $end
$comment Show the parameter values. $end
$dumpall
b110 0
b111 /
b110 .
b110 $
b111 #
b110 "
$end
#0
$dumpvars
bx 2
bx 1
b0 -
b0 ,
b0 +
0*
0)
b0 (
1'
b0 &
b0 %
bx !
$end
#10
0'
#20
b0 1
1'
b1 &
b1 ,
1)
1*
b1 (
b1 -
#30
0'
#40
1'
#50
0'
#60
1'
b1 %
b1 +
b10 &
b10 ,
0)
0*
b10 (
b10 -
#70
0'
#80
1'
#90
0'
#100
b10 1
1'
b10 %
b10 +
b101 &
b101 ,
1)
1*
b11 (
b11 -
#110
0'
#120
1'
#130
0'
#140
b11 !
b11 2
b101 1
1'
b101 %
b101 +
b10 &
b10 ,
b100 (
b100 -
#150
0'
#160
1'
#170
0'
#180
1'
b10 %
b10 +
b100 &
b100 ,
0)
b101 (
b101 -
#190
0'
#200
1'
#210
0'
#220
1'
b100 %
b100 +
b11 &
b11 ,
b100111 (
b100111 -
#230
0'
#240
1'
#250
0'
#260
b11 !
b11 2
b11 1
1'
b11 %
b11 +
1)
0*
b0 (
b0 -
#270
0'
#280
b100111 !
b100111 2
1'
#290
0'
#300
1'
b101 %
b101 +
0)
